llama3/__init__.py
llama3/config.py
llama3/model.py
llama3/utils.py
llama3_package-0.4.0.dist-info/METADATA
llama3_package-0.4.0.dist-info/WHEEL
llama3_package-0.4.0.dist-info/top_level.txt
llama3_package-0.4.0.dist-info/RECORD
