Metadata-Version: 2.1
Name: llama3-package
Version: 0.4.0
Summary: A Python package to interact with Llama 3 locally using Ollama.
Home-page: https://github.com/princeDisant/llama3_package
Author: Disant Upadhyay
License: UNKNOWN
Platform: UNKNOWN
Classifier: Programming Language :: Python :: 3
Classifier: License :: OSI Approved :: MIT License
Classifier: Operating System :: OS Independent
Requires-Python: >=3.7
Requires-Dist: langchain
Requires-Dist: notebook
Requires-Dist: ollama
Provides-Extra: dev
Requires-Dist: pytest ; extra == 'dev'
Requires-Dist: pytest-cov ; extra == 'dev'
